README.txt
run.py
setup.py
test/__init__.py
test/test.py
train/__init__.py
train/__main__.py
train/data/__init__.py
train/data/const_value.py
train/data/station_name.py
train/data/trains.py
train/spider/__init__.py
train/spider/fetch_trains.py
train/utils/__init__.py
train/utils/common_util.py
train/utils/tickets_util.py
train_12306.egg-info/PKG-INFO
train_12306.egg-info/SOURCES.txt
train_12306.egg-info/dependency_links.txt
train_12306.egg-info/entry_points.txt
train_12306.egg-info/requires.txt
train_12306.egg-info/top_level.txt